wysiwyg_img/__init__.py
wysiwyg_img/admin.py
wysiwyg_img/apps.py
wysiwyg_img/models.py
wysiwyg_img/migrations/0001_initial.py
wysiwyg_img/migrations/__init__.py
django_wysiwyg_image-0.1.0.dist-info/LICENSE
django_wysiwyg_image-0.1.0.dist-info/METADATA
django_wysiwyg_image-0.1.0.dist-info/WHEEL
django_wysiwyg_image-0.1.0.dist-info/top_level.txt
django_wysiwyg_image-0.1.0.dist-info/RECORD
