Metadata-Version: 2.1
Name: django-wysiwyg-image
Version: 0.1.0
Summary: An easy way to paste images to wysiwyg editors in Django admin interface.
Home-page: https://github.com/YuriyCherniy/django-wysiwyg-image
Author: Yuriy Cherniy
Author-email: amidobox@gmail.com
License: UNKNOWN
Platform: UNKNOWN
Requires-Python: >=3.6
License-File: LICENSE
